pybarid/__init__.py
pybarid/client.py
pybarid/exceptions.py
pybarid/models.py
pybarid-0.1.0.dist-info/METADATA
pybarid-0.1.0.dist-info/WHEEL
pybarid-0.1.0.dist-info/top_level.txt
pybarid-0.1.0.dist-info/RECORD
